torch_submit/__init__.py
torch_submit/_version.py
torch_submit/cli.py
torch_submit/config.py
torch_submit/connection.py
torch_submit/executor.py
torch_submit/job.py
torch_submit/types.py
torch_submit/utils.py
torch_submit/commands/__init__.py
torch_submit/commands/cluster.py
torch_submit/commands/database.py
torch_submit/commands/job.py
torch_submit-0.1.24.dist-info/LICENSE
torch_submit-0.1.24.dist-info/METADATA
torch_submit-0.1.24.dist-info/WHEEL
torch_submit-0.1.24.dist-info/entry_points.txt
torch_submit-0.1.24.dist-info/top_level.txt
torch_submit-0.1.24.dist-info/RECORD
