Metadata-Version: 2.1
Name: torch-submit
Version: 0.1.24
Summary: A tool for submitting and managing distributed PyTorch jobs
Author-email: Tony Francis <tony@dream3d.com>
License: MIT
Project-URL: Homepage, https://github.com/dream3d-ai/torch-submit
Project-URL: Bug Tracker, https://github.com/dream3d-ai/torch-submit/issues
Keywords: pytorch,distributed,job submission
Classifier: Programming Language :: Python :: 3
Classifier: License :: OSI Approved :: MIT License
Classifier: Operating System :: OS Independent
Requires-Python: >=3.7
License-File: LICENSE
Requires-Dist: typer
Requires-Dist: rich
Requires-Dist: pyyaml
Requires-Dist: fabric
Requires-Dist: sqlalchemy
Requires-Dist: psycopg2-binary
Requires-Dist: optuna
Requires-Dist: optuna-dashboard
